DeepDR/CellEncoder.py
DeepDR/Data.py
DeepDR/DrugEncoder.py
DeepDR/FusionModule.py
DeepDR/Model.py
DeepDR/_DAE_pretrain.py
DeepDR/_MPG_loader.py
DeepDR/_MPG_message_passing.py
DeepDR/_MPG_mha.py
DeepDR/_MPG_model.py
DeepDR/_MPG_util.py
DeepDR/_Prediction.py
DeepDR/_Preprocess.py
DeepDR/_Training.py
DeepDR/_TrimNet_model.py
DeepDR/__init__.py
DeepDR/DefaultData/CCLE_ActArea.csv
DeepDR/DefaultData/CCLE_IC50.csv
DeepDR/DefaultData/DAE.pt
DeepDR/DefaultData/GDSC1_AUC.csv
DeepDR/DefaultData/GDSC1_IC50.csv
DeepDR/DefaultData/GDSC2_AUC.csv
DeepDR/DefaultData/GDSC2_IC50.csv
DeepDR/DefaultData/GDSC_CNV.pkl
DeepDR/DefaultData/GDSC_EXP.pkl
DeepDR/DefaultData/GDSC_MUT.pkl
DeepDR/DefaultData/GDSC_PES.pkl
DeepDR/DefaultData/MPG_dict.pkl
DeepDR/DefaultData/SMILES_dict.pkl
DeepDR/DefaultData/key.genes.txt
deepdr-2.0.1.dist-info/METADATA
deepdr-2.0.1.dist-info/WHEEL
deepdr-2.0.1.dist-info/top_level.txt
deepdr-2.0.1.dist-info/RECORD
